oscplotlib/__init__.py
oscplotlib-0.1.0.dist-info/LICENSE
oscplotlib-0.1.0.dist-info/METADATA
oscplotlib-0.1.0.dist-info/WHEEL
oscplotlib-0.1.0.dist-info/top_level.txt
oscplotlib-0.1.0.dist-info/RECORD
