Metadata-Version: 2.1
Name: oscplotlib
Version: 0.1.0
Summary: OSC1337 wrapper for Matplotlib
Home-page: https://github.com/jtcbrule/oscplotlib
Author: Joshua Brule
Author-email: jtcbrule@gmail.com
License: UNKNOWN
Platform: UNKNOWN
Classifier: Programming Language :: Python :: 3
Classifier: License :: OSI Approved :: MIT License
Classifier: Operating System :: OS Independent
Requires-Python: >=3
Requires-Dist: matplotlib
